requirements/requirements.txt
requirements/test_requirements.txt
titanic_model/VERSION
titanic_model/__init__.py
titanic_model/config.yml
titanic_model/cross_validation.py
titanic_model/pipeline.py
titanic_model/predict.py
titanic_model/train_pipeline.py
titanic_model/tune_pipeline.py
titanic_model/config/__init__.py
titanic_model/config/core.py
titanic_model/datasets/test.csv
titanic_model/datasets/train.csv
titanic_model/processing/__init__.py
titanic_model/processing/data_manager.py
titanic_model/processing/features.py
titanic_model/processing/validation.py
titanic_model/trained_models/titanic_model_output_v1.1.0.pkl
titanic_model-1.1.0.dist-info/licenses/LICENSE
titanic_model-1.1.0.dist-info/METADATA
titanic_model-1.1.0.dist-info/WHEEL
titanic_model-1.1.0.dist-info/top_level.txt
titanic_model-1.1.0.dist-info/RECORD
