Metadata-Version: 2.4
Name: titanic-model
Version: 1.1.0
Summary: Titanic model package.
Author-email: Emin Tagiev <emin.tagiev@phystech.edu>
License-Expression: MIT
Project-URL: Homepage, https://github.com/Emilien-mipt/titanic-package
Classifier: Programming Language :: Python
Classifier: Programming Language :: Python :: 3
Classifier: Programming Language :: Python :: 3.13
Classifier: Programming Language :: Python :: Implementation :: CPython
Classifier: Programming Language :: Python :: Implementation :: PyPy
Requires-Python: >=3.10.0
License-File: LICENSE
Requires-Dist: feature-engine==1.8.3
Requires-Dist: joblib==1.5.0
Requires-Dist: numpy==2.2.6
Requires-Dist: pandas==2.2.3
Requires-Dist: pydantic==2.11.4
Requires-Dist: scikit-learn==1.6.1
Requires-Dist: PyYAML==6.0.2
Requires-Dist: types-PyYAML==6.0.12.20250516
Provides-Extra: test
Requires-Dist: pytest==8.3.5; extra == "test"
Requires-Dist: tox==4.26.0; extra == "test"
Provides-Extra: dev
Requires-Dist: black==25.1.0; extra == "dev"
Requires-Dist: flake8==7.2.0; extra == "dev"
Requires-Dist: isort==6.0.1; extra == "dev"
Requires-Dist: mypy==1.15.0; extra == "dev"
Requires-Dist: pytest==8.3.5; extra == "dev"
Requires-Dist: tox==4.26.0; extra == "dev"
Dynamic: license-file
